entsog/__init__.py
entsog/decorators.py
entsog/entsog.py
entsog/exceptions.py
entsog/mappings.py
entsog/misc.py
entsog/parsers.py
entsog/plot_utils.py
entsog_py-1.0.3.dist-info/LICENSE
entsog_py-1.0.3.dist-info/METADATA
entsog_py-1.0.3.dist-info/WHEEL
entsog_py-1.0.3.dist-info/top_level.txt
entsog_py-1.0.3.dist-info/RECORD
