Metadata-Version: 2.1
Name: entsog-py
Version: 1.0.3
Summary: A python API wrapper for transparency.entsog.eu
Home-page: https://github.com/nhcb/entsog-py
Author: Nicky Sonnemans
Author-email: nicky.sonnemans@gmail.nl
License: MIT
Keywords: entsog api gas energy
Classifier: Development Status :: 3 - Alpha
Classifier: Intended Audience :: Developers
Classifier: Topic :: Scientific/Engineering
Classifier: License :: OSI Approved :: MIT License
Classifier: Programming Language :: Python :: 3.8
Classifier: Programming Language :: Python :: 3.9
License-File: LICENSE
Requires-Dist: requests
Requires-Dist: pandas
Requires-Dist: bs4
Requires-Dist: unidecode
